diffiehellmanlib-5.0.1.dist-info/METADATA
diffiehellmanlib-5.0.1.dist-info/WHEEL
diffiehellmanlib-5.0.1.dist-info/licenses/LICENSE
src/lib.rs
pyproject.toml
diffiehellmanlib.pyi
LICENSE
Cargo.toml
Cargo.lock
diffiehellmanlib/__init__.py
diffiehellmanlib/__init__.pyi
diffiehellmanlib/py.typed
diffiehellmanlib/diffiehellmanlib.cp312-win_amd64.pyd
diffiehellmanlib-5.0.1.dist-info/RECORD
