Metadata-Version: 2.4
Name: diffiehellmanlib
Version: 5.0.1
Classifier: Programming Language :: Rust
Classifier: Programming Language :: Python :: 3
Classifier: License :: OSI Approved :: MIT License
Classifier: Operating System :: OS Independent
License-File: LICENSE
Summary: Diffie-Hellman key exchange library
Author: Gorshkov Kostantin <kostya_gorshkov_06@vk.com>
Author-email: Gorshkov Kostantin <kostya_gorshkov_06@vk.com>
License: MIT
Requires-Python: >=3.7
Project-URL: Source Code, https://github.com/kostya2023/diffiehellmanlib
